ndh/__init__.py
ndh/context_processors.py
ndh/forms.py
ndh/mail.py
ndh/mixins.py
ndh/models.py
ndh/py.typed
ndh/querysets.py
ndh/tests.py
ndh/utils.py
ndh/widgets.py
ndh/locale/fr/LC_MESSAGES/django.mo
ndh/locale/fr/LC_MESSAGES/django.po
ndh/static/css/ndh.css
ndh/templates/ndh.html
ndh/templates/ndh/base_delete.html
ndh/templates/ndh/base_form.html
ndh/templates/ndh/delete.html
ndh/templates/ndh/dt.html
ndh/templates/ndh/form.html
ndh/templates/ndh/formset.html
ndh/templates/ndh/tables.html
ndh/templates/ndh/forms/widgets/datalist.html
ndh/templates/registration/activation_email.html
ndh/templates/registration/activation_email.txt
ndh/templates/registration/logged_out.html
ndh/templates/registration/login.html
ndh/templates/registration/password_reset_complete.html
ndh/templates/registration/password_reset_confirm.html
ndh/templates/registration/password_reset_done.html
ndh/templates/registration/password_reset_email.html
ndh/templates/registration/password_reset_form.html
ndh/templatetags/__init__.py
ndh/templatetags/ndh.py
ndh-6.11.0.dist-info/METADATA
ndh-6.11.0.dist-info/WHEEL
ndh-6.11.0.dist-info/licenses/LICENSE
ndh-6.11.0.dist-info/RECORD
