Metadata-Version: 2.4
Name: ndh
Version: 6.11.0
Summary: Nim's Django Helpers
Project-URL: Changelog, https://github.com/nim65s/ndh/blob/master/CHANGELOG.md
Project-URL: Documentation, https://ndh.readthedocs.io/
Project-URL: Homepage, https://github.com/nim65s/ndh
Project-URL: Repository, https://github.com/nim65s/ndh.git
Author-email: Guilhem Saurel <guilhem.saurel@laas.fr>
License-Expression: BSD-2-Clause
License-File: LICENSE
Requires-Python: >=3.10
Requires-Dist: django-autoslug>=1.9.9
Requires-Dist: django-bootstrap5>=24.3
